[
    { "flightNo" :1,  "flightZdate" :"2009-09-01",  "legNo" :12,  "origin" :"MSS",  "destination" :"trichy",  "releaseNumber" :1,  "releaseTime" :"2014-07-11 18:53:56"},
    { "flightNo" :2,  "flightZdate" :"2017-01-01",  "legNo" :321,  "origin" :"TSB",  "destination" :"UBV",  "releaseNumber" :6,  "releaseTime" :"2014-07-11 18:53:56"},
    { "flightNo" :3,  "flightZdate" :"2008-11-01",  "legNo" :2,  "origin" :"WRE",  "destination" :"KVA",  "releaseNumber" :2,  "releaseTime" :"2014-07-11 18:53:56"},
    { "flightNo" :4,  "flightZdate" :"2017-09-01",  "legNo" :321,  "origin" :"KVA",  "destination" :"AND",  "releaseNumber" :3,  "releaseTime" :"2014-07-11 18:53:56"},
    { "flightNo" :5,  "flightZdate" :"2018-02-12",  "legNo" :4,  "origin" :"UBV",  "destination" :"DEH",  "releaseNumber" :4,  "releaseTime" :"2014-07-11 18:53:56"},
    { "flightNo" :6,  "flightZdate" :"2017-09-01",  "legNo" :321,  "origin" :"TSB",  "destination" :"WRE",  "releaseNumber" :1,  "releaseTime" :"2014-07-11 18:53:56"},
    { "flightNo" :7,  "flightZdate" :"2017-12-01",  "legNo" :53,  "origin" :"KVA",  "destination" :"UBV",  "releaseNumber" :7,  "releaseTime" :"2014-07-11 18:53:56"},
    { "flightNo" :8,  "flightZdate" :"2017-09-01",  "legNo" :321,  "origin" :"JKI",  "destination" :"JKI",  "releaseNumber" :4,  "releaseTime" :"2014-07-11 18:53:56"},
    { "flightNo" :9,  "flightZdate" :"2020-06-11",  "legNo" :12,  "origin" :"UBV",  "destination" :"UBV",  "releaseNumber" :1,  "releaseTime" :"2014-07-11 18:53:56"},
    { "flightNo" :10,  "flightZdate" :"2021-01-31",  "legNo" :23,  "origin" :"UEY",  "destination" :"KVA",  "releaseNumber" :2,  "releaseTime" :"2014-07-11 18:53:56"},
    { "flightNo" :12,  "flightZdate" :"2017-09-01",  "legNo" :321,  "origin" :"TSB",  "destination" :"UBV",  "releaseNumber" :3,  "releaseTime" :"2014-07-11 18:53:56"},
    { "flightNo" :11,  "flightZdate" :"2004-10-01",  "legNo" :45,  "origin" :"DEH",  "destination" :"KVA",  "releaseNumber" :2,  "releaseTime" :"2014-07-11 18:53:56"},
    { "flightNo" :13,  "flightZdate" :"2017-09-01",  "legNo" :321,  "origin" :"KVA",  "destination" :"UBV",  "releaseNumber" :2,  "releaseTime" :"2014-07-11 18:53:56"}
]